pipsi.py
pipsi-0.9.dist-info/DESCRIPTION.rst
pipsi-0.9.dist-info/metadata.json
pipsi-0.9.dist-info/RECORD
pipsi-0.9.dist-info/top_level.txt
pipsi-0.9.dist-info/WHEEL
pipsi-0.9.dist-info/entry_points.txt
pipsi-0.9.dist-info/METADATA
