Metadata-Version: 2.0
Name: pipsi
Version: 0.9
Summary: Wraps pip and virtualenv to install scripts
Home-page: http://github.com/mitsuhiko/pipsi/
Author: Armin Ronacher
Author-email: armin.ronacher@active-4.com
License: BSD
Platform: UNKNOWN
Requires-Dist: Click
Requires-Dist: virtualenv
